pystocklib/__init__.py
pystocklib/common/__init__.py
pystocklib/srim/__init__.py
pystocklib/srim/reader.py
pystocklib-0.0.5.dist-info/METADATA
pystocklib-0.0.5.dist-info/WHEEL
pystocklib-0.0.5.dist-info/top_level.txt
pystocklib-0.0.5.dist-info/RECORD
